{"timestamps":{"11-16-2021":["11-16-2021","https://www.twitch.tv/videos/1206778475",{"game":"REACT RAAL","time":"15m50s"},{"game":"LSF REACT","time":"47m40s"},{"game":"CLEANING HIS ROOM","time":"52m13s"},{"game":"CRAB GAME","time":"2h15m13s"},{"game":"HALO INFINITE","time":"3h16m10s"},{"game":"MORE VIDEOS","time":"5h16m55s"},{"game":"NOPIXEL RP (JP)","time":"6h9m16s"},{"game":"LOWER VAULT HEIST (RP)","time":"7h33m28s"}],"11-17-2021":["11-17-2021","https://www.twitch.tv/videos/1207686293",{"game":"REACT ROON","time":"9m05s"},{"game":"THE GAME AWARDS","time":"26m6s"},{"game":"LSF REACT","time":"1h0m40s"},{"game":"MINECRAFT SPEEDRUNS","time":"1h50m15s"},{"game":"MORE VIDEOS","time":"3h37m42s"},{"game":"CRAB GAME","time":"3h58m10s"},{"game":"EVEN MORE VIDEOS","time":"4h4m57s"},{"game":"HALO INFINITE W/ MOXY","time":"5h3m15s"},{"game":"VIDEOS W/ MOXY","time":"7h4m34s"},{"game":"THE MORTUARY ASSISTANT","time":"8h12m54s"},{"game":"APEX LEGENDS","time":"8h51m20s"}],"11-18-2021":["11-18-2021","https://www.twitch.tv/videos/1208521061",{"game":"LSF RECAP","time":"11m17s"},{"game":"REACT RORY","time":"23m55s"},{"game":"R/XQCOW","time":"37m52s"},{"game":"BEAMNG.DRIVE","time":"2h9m40s"},{"game":"STALL GAMES","time":"3h34m30s"},{"game":"THE ASYLUM INCIDENT","time":"4h14m36s"},{"game":"MORE VIDEOS","time":"5h21m18s"},{"game":"NOPIXEL RP (JP)","time":"7h31m25s"},{"game":"UPPER VAULT HEIST (RP)","time":"8h51m35s"}],"11-19-2021":["11-19-2021","https://www.twitch.tv/videos/1209561944",{"game":"LSF REACT","time":"9m30s"},{"game":"REACT RAMP","time":"27m22s"},{"game":"FORTNITE","time":"1h35m38s"},{"game":"CRAB GAME","time":"2h1m12s"},{"game":"MARBLES ON STREAM","time":"2h41m21s"},{"game":"POKÉMON BRILLIANT DIAMOND","time":"3h19m10s"},{"game":"MORE VIDEOS","time":"5h44m02s"},{"game":"NOPIXEL RP (JP)","time":"6h4m49s"},{"game":"VAULT HEIST (RP)","time":"6h50m"},{"game":"MORE LSF","time":"14h11m0s"},{"game":"REACT RAMOS","time":"14h25m25s"},{"game":"MINECRAFT SPEEDRUNS","time":"16h9m14s"},{"game":"VIDEOS W/ POKE","time":"17h0m44s"},{"game":"CAR WARS W/ POKE","time":"17h48m23s"},{"game":"APEX LEGENDS W/ POKE & MOXY","time":"18h48m9s"},{"game":"VIDEOS W/ POKE & MOXY","time":"20h33m15s"},{"game":"LEAGUE OF LEGENDS W/ MOXY & POKE","time":"20h52m21s"}],"11-21-2021":["11-21-2021","https://www.twitch.tv/videos/1211575130",{"game":"REACT ROOT","time":"4m35s"},{"game":"LSF REACT","time":"29m55s"},{"game":"R/XQCOW","time":"38m22s"},{"game":"THE FOREST (W/POKE AND MOXY)","time":"2h20m16s"},{"game":"MORE VIDEOS","time":"5h55m7s"},{"game":"RISK","time":"6h13m6s"},{"game":"MARBLES ON STREAM","time":"6h34m48s"},{"game":"VALORANT","time":"7h32m58s"}],"1-11-2022":["1-11-2022","https://www.twitch.tv/videos/1259758382",{"game":"LSF REACT","time":"9m20s"},{"game":"R/XQCOW","time":"30m11s"},{"game":"REACT ING","time":"34m15s"},{"game":"MASTERCHEF","time":"55m43s"},{"game":"NOPIXEL RP (JP)","time":"1h55m38s"},{"game":"C22 RETURNS (RP)","time":"4h14m30s"},{"game":"EMOTE FARMING SIMULATOR","time":"4h37m44s"},{"game":"LEAGUE","time":"5h13m54s"},{"game":"ESCAPE FROM TARKOV","time":"7h11m32s"}],"1-12-2022":["1-12-2022","https://www.twitch.tv/videos/1260995579",{"game":"LSF RECAP","time":"13m25s"},{"game":"R/XQCOW","time":"32m34s"},{"game":"REACT RAMEE","time":"39m40s"},{"game":"MASTERCHEF","time":"1h12m46s"},{"game":"THE COIN GAME","time":"3h27m46s"},{"game":"AIM LAB W/POKE","time":"4h10m35s"},{"game":"VALORANT W/POKE","time":"4h53m32s"},{"game":"APEX LEGENDS W/POKE","time":"5h30m8s"},{"game":"LEAGUE OF LEGENDS W/POKE","time":"6h2m37s"},{"game":"VIDEOS","time":"8h32m1s"},{"game":"BIG BRAIN ACADEMY","time":"9h40m15s"},{"game":"CLUBHOUSE GAMES","time":"10h13m3s"},{"game":"ELECTRICIAN SIMULATOR","time":"11h5m13s"},{"game":"THIEF SIMULATOR 2","time":"11h34m41s"},{"game":"HUNTER X HUNTER","time":"12h13m17s"},{"game":"NOPIXEL RP (JP)","time":"15h11m1s"},{"game":"UPPER VAULT HEIST (RP)","time":"16h21m25s"}]}}
